{
    "1": {
        "date": "February 1, 2021",
        "tourn_name": "Rapid Monthly Osu Tournament 54",
        "team_name": "",
        "forum": "https://osu.ppy.sh/community/forums/topics/1243801?n=1",
        "tourn_sheet": "",
        "bracket": "https://challonge.com/rmosutourney54",
        "rank_range": "30k-70k",
        "seed": "N/A",
        "format": "1v1",
        "team_size": 1,
        "placement": "3rd Place",
        "misc": "",
        "notes": "good times, found alex and also met hlv though i didnt know it at the time",
        "p1": 16626263,
        "p2": "",
        "p3": "",
        "p4": "",
        "p5": "",
        "p6": "",
        "p7": "",
        "p8": "",
        "p9": "",
        "p10": "",
        "p11": "",
        "p12": "",
        "p13": "",
        "p14": "",
        "p15": "",
        "p16": ""
    },
    "2": {
        "date": "March 26, 2021",
        "tourn_name": "Gary's Spring Hidden Tournament",
        "team_name": "",
        "forum": "https://osu.ppy.sh/community/forums/topics/1266715?n=1",
        "tourn_sheet": "https://docs.google.com/spreadsheets/d/1g3jauHvuq_ldSGtzvi4kHvGch9t4tAFjPOCVWEesVnc/edit#gid=0",
        "bracket": "https://challonge.com/nofiqqoi",
        "rank_range": "10k-50k",
        "seed": "DNQ",
        "format": "1v1",
        "team_size": 1,
        "placement": "DNQ",
        "misc": "all hidden",
        "notes": "this started my hidden spree",
        "p1": 16626263,
        "p2": "",
        "p3": "",
        "p4": "",
        "p5": "",
        "p6": "",
        "p7": "",
        "p8": "",
        "p9": "",
        "p10": "",
        "p11": "",
        "p12": "",
        "p13": "",
        "p14": "",
        "p15": "",
        "p16": ""
    },
    "3": {
        "date": "May 1, 2021",
        "tourn_name": "RMoT Invitational #14",
        "team_name": "",
        "forum": "https://osu.ppy.sh/community/forums/topics/1298219?n=1",
        "tourn_sheet": "",
        "bracket": "",
        "rank_range": "20k-75k",
        "seed": "idr",
        "format": "1v1",
        "team_size": 1,
        "placement": "3rd Place",
        "misc": "invitational",
        "notes": "had a good time and went out with a good match",
        "p1": 16626263,
        "p2": "",
        "p3": "",
        "p4": "",
        "p5": "",
        "p6": "",
        "p7": "",
        "p8": "",
        "p9": "",
        "p10": "",
        "p11": "",
        "p12": "",
        "p13": "",
        "p14": "",
        "p15": "",
        "p16": ""
    },
    "4": {
        "date": "May 7, 2021",
        "tourn_name": "WhiteCat Official Osu tournament Low Tier",
        "team_name": "Hard n' Stiff",
        "forum": "https://osu.ppy.sh/community/forums/topics/1298947?n=1",
        "tourn_sheet": "https://docs.google.com/spreadsheets/d/1z9QN6kxRpgyBhjM1ZA2_kxqi9AUz2KSEHoBSJrHNRoI/edit#gid=315565972",
        "bracket": "https://challonge.com/WCOTlow",
        "rank_range": "30k+",
        "seed": "25/64",
        "format": "2v2",
        "team_size": 4,
        "placement": "Round of 16",
        "misc": "",
        "notes": "first team tourney also first tourney i deranked for",
        "p1": 16626263,
        "p2": 8418054,
        "p3": 13782969,
        "p4": 17010453,
        "p5": "",
        "p6": "",
        "p7": "",
        "p8": "",
        "p9": "",
        "p10": "",
        "p11": "",
        "p12": "",
        "p13": "",
        "p14": "",
        "p15": "",
        "p16": ""
    },
    "5": {
        "date": "May 21, 2021",
        "tourn_name": "Free-For-All osu! Tournament #4",
        "team_name": "",
        "forum": "https://osu.ppy.sh/community/forums/topics/1295824?n=1",
        "tourn_sheet": "https://docs.google.com/spreadsheets/d/1JGg_geS6CzlIOVIrIaqpVioYYT9-zAcmHl21hYyPLC8/edit#gid=1539134114",
        "bracket": "",
        "rank_range": "23k-40k",
        "seed": "N/A",
        "format": "FFA",
        "team_size": 1,
        "placement": "Round of 32",
        "misc": "battle royale",
        "notes": "!?",
        "p1": 16626263,
        "p2": "",
        "p3": "",
        "p4": "",
        "p5": "",
        "p6": "",
        "p7": "",
        "p8": "",
        "p9": "",
        "p10": "",
        "p11": "",
        "p12": "",
        "p13": "",
        "p14": "",
        "p15": "",
        "p16": ""
    },
    "6": {
        "date": "June 16, 2021",
        "tourn_name": "Rapid Monthly osu! Tournament #58",
        "team_name": "",
        "forum": "https://osu.ppy.sh/community/forums/topics/1350410?n=1",
        "tourn_sheet": "",
        "bracket": "https://challonge.com/rmosutourney58",
        "rank_range": "30k-70k",
        "seed": "N/A",
        "format": "1v1",
        "team_size": 1,
        "placement": "Quarterfinals",
        "misc": "",
        "notes": "F",
        "p1": 16626263,
        "p2": "",
        "p3": "",
        "p4": "",
        "p5": "",
        "p6": "",
        "p7": "",
        "p8": "",
        "p9": "",
        "p10": "",
        "p11": "",
        "p12": "",
        "p13": "",
        "p14": "",
        "p15": "",
        "p16": ""
    },
    "7": {
        "date": "June 25, 2021",
        "tourn_name": "Villoux Tournament #9",
        "team_name": "",
        "forum": "https://osu.ppy.sh/community/forums/topics/1329702?n=1",
        "tourn_sheet": "",
        "bracket": "",
        "rank_range": "25k-60k",
        "seed": "N/A",
        "format": "1v1",
        "team_size": 1,
        "placement": "Round of 64",
        "misc": "",
        "notes": "worlds biggest hard rock hater",
        "p1": 16626263,
        "p2": "",
        "p3": "",
        "p4": "",
        "p5": "",
        "p6": "",
        "p7": "",
        "p8": "",
        "p9": "",
        "p10": "",
        "p11": "",
        "p12": "",
        "p13": "",
        "p14": "",
        "p15": "",
        "p16": ""
    },
    "8": {
        "date": "September 1, 2021",
        "tourn_name": "RMoT Invitational #15",
        "team_name": "",
        "forum": "https://osu.ppy.sh/community/forums/topics/1400042",
        "tourn_sheet": "",
        "bracket": "",
        "rank_range": "20k-75k",
        "seed": "15/16",
        "format": "1v1",
        "team_size": 1,
        "placement": "Quarterfinals",
        "misc": "invitational",
        "notes": "was asleep",
        "p1": 16626263,
        "p2": "",
        "p3": "",
        "p4": "",
        "p5": "",
        "p6": "",
        "p7": "",
        "p8": "",
        "p9": "",
        "p10": "",
        "p11": "",
        "p12": "",
        "p13": "",
        "p14": "",
        "p15": "",
        "p16": ""
    },
    "9": {
        "date": "October 1, 2021",
        "tourn_name": "Osu Big PP Tournament 2 ",
        "team_name": "",
        "forum": "https://osu.ppy.sh/community/forums/topics/1059993?n=1",
        "tourn_sheet": "https://docs.google.com/spreadsheets/d/1Ybax28oks4fMenGasYb-FkiT4L8zX39CcuhlEyxVoLo/edit#gid=1166113552",
        "bracket": "https://challonge.com/OBPPT2",
        "rank_range": "10k-50k",
        "seed": "9/64",
        "format": "1v1",
        "team_size": 1,
        "placement": "Semifinals",
        "misc": "",
        "notes": "played pretty well. tiebreaker losses: 1",
        "p1": 16626263,
        "p2": "",
        "p3": "",
        "p4": "",
        "p5": "",
        "p6": "",
        "p7": "",
        "p8": "",
        "p9": "",
        "p10": "",
        "p11": "",
        "p12": "",
        "p13": "",
        "p14": "",
        "p15": "",
        "p16": ""
    },
    "10": {
        "date": "October 16, 2021",
        "tourn_name": "Deko's Loli Cup",
        "team_name": "",
        "forum": "https://osu.ppy.sh/community/forums/topics/1418536?n=1",
        "tourn_sheet": "https://docs.google.com/spreadsheets/d/1FxFnZmLqhEZo1WmBreNYgyIq4g8H8O7vMQ6yu1LtsCM/edit#gid=1217761768",
        "bracket": "https://challonge.com/lolihump",
        "rank_range": "10k-50k",
        "seed": "62/64",
        "format": "1v1",
        "team_size": 1,
        "placement": "Round of 64",
        "misc": "",
        "notes": "L",
        "p1": 16626263,
        "p2": "",
        "p3": "",
        "p4": "",
        "p5": "",
        "p6": "",
        "p7": "",
        "p8": "",
        "p9": "",
        "p10": "",
        "p11": "",
        "p12": "",
        "p13": "",
        "p14": "",
        "p15": "",
        "p16": ""
    },
    "11": {
        "date": "October 16, 2021",
        "tourn_name": "osu! Collegiate League Fall 2021",
        "team_name": "The University of California - Irvine",
        "forum": "https://osu.ppy.sh/community/forums/topics/1418038?n=1",
        "tourn_sheet": "https://docs.google.com/spreadsheets/d/13Surp300sCHr4B9vKjFBVUocVNnzOqbCmgFGoy-y7XE/edit#gid=1317140078",
        "bracket": "",
        "rank_range": "uhh",
        "seed": "13/28",
        "format": "2v2",
        "team_size": 4,
        "placement": "Quarterfinals",
        "misc": "",
        "notes": "met newb :D",
        "p1": 12437342,
        "p2": 10350809,
        "p3": 5056999,
        "p4": 16626263,
        "p5": "",
        "p6": "",
        "p7": "",
        "p8": "",
        "p9": "",
        "p10": "",
        "p11": "",
        "p12": "",
        "p13": "",
        "p14": "",
        "p15": "",
        "p16": ""
    },
    "12": {
        "date": "October 17, 2021",
        "tourn_name": "What If... osu! World Cup 2015 was played by 5 digits?",
        "team_name": "saggers",
        "forum": "https://osu.ppy.sh/community/forums/topics/1422329?n=1",
        "tourn_sheet": "https://docs.google.com/spreadsheets/d/1SKl2VqeNuZH598hzkAyAHJu_CtrLW2XspJJtLHJfD5s/edit#gid=0",
        "bracket": "",
        "rank_range": "10k-99k",
        "seed": "DNQ",
        "format": "4v4",
        "team_size": 8,
        "placement": "Group Stage",
        "misc": "owc 2015 rules",
        "notes": "schedule hell",
        "p1": 16626263,
        "p2": 13782969,
        "p3": 11782233,
        "p4": 14932209,
        "p5": 6784744,
        "p6": 9641273,
        "p7": 15796522,
        "p8": "",
        "p9": "",
        "p10": "",
        "p11": "",
        "p12": "",
        "p13": "",
        "p14": "",
        "p15": "",
        "p16": ""
    },
    "13": {
        "date": "October 22, 2021",
        "tourn_name": "Glitchy Osu Tournament",
        "team_name": "Your Mother",
        "forum": "https://osu.ppy.sh/community/forums/topics/1427756?n=1",
        "tourn_sheet": "https://docs.google.com/spreadsheets/d/1almVdd0IS2OSKFu1fer2vc6N7Rla2gIFsvvnemhV1Ew/edit#gid=1223899141",
        "bracket": "https://www.google.com/url?q=https://challonge.com/de/GOT_2021&sa=D&source=editors&ust=1665551868211613&usg=AOvVaw1vWgkoUX7LBKucar72dXDw",
        "rank_range": "10k-99k",
        "seed": "45/64",
        "format": "3v3",
        "team_size": 6,
        "placement": "Round of 32",
        "misc": "each stage has a \"glitch\"",
        "notes": "met a lot of people here! some good, some bad, some ugly...",
        "p1": 12632416,
        "p2": 15885448,
        "p3": 5427223,
        "p4": 4756779,
        "p5": 10976433,
        "p6": 16626263,
        "p7": "",
        "p8": "",
        "p9": "",
        "p10": "",
        "p11": "",
        "p12": "",
        "p13": "",
        "p14": "",
        "p15": "",
        "p16": ""
    },
    "14": {
        "date": "December 31, 2021",
        "tourn_name": "Binfy's 5 Digit Bracket",
        "team_name": "Kusudama",
        "forum": "https://osu.ppy.sh/community/forums/topics/1482422?n=1",
        "tourn_sheet": "https://docs.google.com/spreadsheets/d/1JilPOCqondFluKxKplo_JbR8kK1rOx_yl05FyKpBpc0/edit#gid=1341172268",
        "bracket": "https://challonge.com/BFBa",
        "rank_range": "10k-99k",
        "seed": "33/64",
        "format": "4v4",
        "team_size": 6,
        "placement": "Semifinals",
        "misc": "\"derankers\" screened out ",
        "notes": "and why does ",
        "p1": 14396453,
        "p2": 8779023,
        "p3": 9367683,
        "p4": 8921554,
        "p5": 10382679,
        "p6": 16626263,
        "p7": "",
        "p8": "",
        "p9": "",
        "p10": "",
        "p11": "",
        "p12": "",
        "p13": "",
        "p14": "",
        "p15": "",
        "p16": ""
    },
    "15": {
        "date": "January 1, 2022",
        "tourn_name": "Merami Household Winter Cup",
        "team_name": "mermommy",
        "forum": "https://osu.ppy.sh/community/forums/topics/1455536?n=1",
        "tourn_sheet": "https://docs.google.com/spreadsheets/d/1jhFVfsLEvFAt3axM4Fencwo2tSSvW9NCH9Yqkjq7H_s/edit#gid=0",
        "bracket": "https://challonge.com/MHWC21",
        "rank_range": "1k+",
        "seed": "60/64",
        "format": "2v2",
        "team_size": 3,
        "placement": "Round of 32",
        "misc": "",
        "notes": "1k was pretty hard who wouldve thought",
        "p1": 16626263,
        "p2": 6784744,
        "p3": 7438459,
        "p4": "",
        "p5": "",
        "p6": "",
        "p7": "",
        "p8": "",
        "p9": "",
        "p10": "",
        "p11": "",
        "p12": "",
        "p13": "",
        "p14": "",
        "p15": "",
        "p16": ""
    },
    "16": {
        "date": "January 29, 2022",
        "tourn_name": "Broccoli Cup 2",
        "team_name": "Uprankers",
        "forum": "https://osu.ppy.sh/community/forums/topics/1479033?n=1",
        "tourn_sheet": "https://docs.google.com/spreadsheets/d/1IrImSc3LFpqD5cpFLD62rFn8b1BLTHDQlE7cUi3ToOk/edit#gid=0",
        "bracket": "https://challonge.com/broccers",
        "rank_range": "1.2k+",
        "seed": "15/64",
        "format": "3v3",
        "team_size": 6,
        "placement": "Round of 16",
        "misc": "3 tiers",
        "notes": "probably my best tournament performance ever. tb losses: 3",
        "p1": 17706086,
        "p2": 5283014,
        "p3": 12904237,
        "p4": 6051693,
        "p5": 19607568,
        "p6": 16626263,
        "p7": "",
        "p8": "",
        "p9": "",
        "p10": "",
        "p11": "",
        "p12": "",
        "p13": "",
        "p14": "",
        "p15": "",
        "p16": ""
    },
    "17": {
        "date": "January 29, 2022",
        "tourn_name": "Tayuno's Standout Cup",
        "team_name": "kevin",
        "forum": "https://osu.ppy.sh/community/forums/topics/1492360?n=1",
        "tourn_sheet": "https://docs.google.com/spreadsheets/d/1oWZaQfzNucF0aMMHA0Oupn6z-tFhNjMNJLaIFnw39-s/edit#gid=0",
        "bracket": "https://challonge.com/TayunosStandoutCup",
        "rank_range": "10k-99k",
        "seed": "4/64",
        "format": "N/A",
        "team_size": 4,
        "placement": "Finals",
        "misc": "4v4->3v3->2v2->1v1",
        "notes": "legendary team (also one team member restricted mid tournament :tf:) lost to an emu",
        "p1": 5427223,
        "p2": 10205817,
        "p3": 16626263,
        "p4": "",
        "p5": "",
        "p6": "",
        "p7": "",
        "p8": "",
        "p9": "",
        "p10": "",
        "p11": "",
        "p12": "",
        "p13": "",
        "p14": "",
        "p15": "",
        "p16": ""
    },
    "18": {
        "date": "February 18, 2022",
        "tourn_name": "Love Live Tournament 2",
        "team_name": "",
        "forum": "https://osu.ppy.sh/community/forums/topics/1513400?n=1",
        "tourn_sheet": "https://docs.google.com/spreadsheets/d/15FiSm_BHEK3yM1Qh7Lm6FVlkkcEBlzH1v7sFGjvyQco/edit#gid=1994017804",
        "bracket": "https://challonge.com/lxg1elqd",
        "rank_range": "15k-100k",
        "seed": "2/64",
        "format": "1v1",
        "team_size": 1,
        "placement": "3rd Place",
        "misc": "all maps are love live",
        "notes": "the 3rd place curse officially begins. got cool banner tho",
        "p1": 16626263,
        "p2": "",
        "p3": "",
        "p4": "",
        "p5": "",
        "p6": "",
        "p7": "",
        "p8": "",
        "p9": "",
        "p10": "",
        "p11": "",
        "p12": "",
        "p13": "",
        "p14": "",
        "p15": "",
        "p16": ""
    },
    "19": {
        "date": "March 6, 2022",
        "tourn_name": "Down Bad Cup 1st Edition",
        "team_name": "Turn My Swag On",
        "forum": "",
        "tourn_sheet": "https://docs.google.com/spreadsheets/d/1icty6kMiBrTfIhDdAcbgBoSypuQ1nISjOcf6JCwsI1Y/edit#gid=1491700608",
        "bracket": "https://challonge.com/downbadcup",
        "rank_range": "Open Rank",
        "seed": "1/16",
        "format": "2v2",
        "team_size": 2,
        "placement": "1st Place",
        "misc": "for fun",
        "notes": "i think we played two matches this tournament",
        "p1": 12904237,
        "p2": 16626263,
        "p3": "",
        "p4": "",
        "p5": "",
        "p6": "",
        "p7": "",
        "p8": "",
        "p9": "",
        "p10": "",
        "p11": "",
        "p12": "",
        "p13": "",
        "p14": "",
        "p15": "",
        "p16": ""
    },
    "20": {
        "date": "March 18, 2022",
        "tourn_name": "Gary's Spring Hidden Tournament 2",
        "team_name": "mcdonald super star ultra",
        "forum": "https://osu.ppy.sh/community/forums/topics/1519318?n=1",
        "tourn_sheet": "https://docs.google.com/spreadsheets/d/1Fj8BfIn0bZp1e0qTfjvcr1DtHIO0RiJvcmDlNXWSXgo/edit#gid=0",
        "bracket": "https://challonge.com/xy0f6gj5",
        "rank_range": "5k-30k",
        "seed": "15/32",
        "format": "2v2",
        "team_size": 3,
        "placement": "Quarterfinals",
        "misc": "all hidden",
        "notes": "did pretty good for being at lower end of rank range",
        "p1": 16626263,
        "p2": 10350809,
        "p3": 14396453,
        "p4": "",
        "p5": "",
        "p6": "",
        "p7": "",
        "p8": "",
        "p9": "",
        "p10": "",
        "p11": "",
        "p12": "",
        "p13": "",
        "p14": "",
        "p15": "",
        "p16": ""
    },
    "21": {
        "date": "March 26, 2022",
        "tourn_name": "osu! Player's Choice Tournament 3",
        "team_name": "bomb seal",
        "forum": "https://osu.ppy.sh/community/forums/topics/1528797?n=1",
        "tourn_sheet": "https://docs.google.com/spreadsheets/d/1n2h2M4l0jrSn28tDtzC_SwCnZlfjevMWF1rbs5jFM2g/edit#gid=0",
        "bracket": "https://challonge.com/ubo4nfl8",
        "rank_range": "5k+",
        "seed": "7/32",
        "format": "2v2",
        "team_size": 3,
        "placement": "Semifinals",
        "misc": "maps submitted by players",
        "notes": "awesome teammates :D  tournament was freemod the whole time which was pretty nice",
        "p1": 5427223,
        "p2": 4529885,
        "p3": 16626263,
        "p4": "",
        "p5": "",
        "p6": "",
        "p7": "",
        "p8": "",
        "p9": "",
        "p10": "",
        "p11": "",
        "p12": "",
        "p13": "",
        "p14": "",
        "p15": "",
        "p16": ""
    },
    "22": {
        "date": "March 4, 2022",
        "tourn_name": "Baku's Spring Festival 🌻",
        "team_name": "Pocket Galaxy",
        "forum": "https://osu.ppy.sh/community/forums/topics/1523028?n=1",
        "tourn_sheet": "https://docs.google.com/spreadsheets/d/1MRkGAtCXC1plQqdJs_DwD5pK6SjylsNekbjCFsP4gn8/edit#gid=0",
        "bracket": "https://challonge.com/BSF22",
        "rank_range": "2.5k-20k",
        "seed": "11/64",
        "format": "2v2",
        "team_size": 4,
        "placement": "Quarterfinals",
        "misc": "2 tiers",
        "notes": "thanks for carry onkar",
        "p1": 3426414,
        "p2": 12904237,
        "p3": 7153533,
        "p4": 16626263,
        "p5": "",
        "p6": "",
        "p7": "",
        "p8": "",
        "p9": "",
        "p10": "",
        "p11": "",
        "p12": "",
        "p13": "",
        "p14": "",
        "p15": "",
        "p16": ""
    },
    "23": {
        "date": "April 4, 2022",
        "tourn_name": "copper world cup 1",
        "team_name": "",
        "forum": "",
        "tourn_sheet": "https://docs.google.com/spreadsheets/d/1wE0K-RZvDWZ1GxSe-MO1CdzgqUXOupGKNi5cqA2wqtg/edit",
        "bracket": "https://challonge.com/hl9in0nh",
        "rank_range": "?",
        "seed": "?",
        "format": "1v1",
        "team_size": 1,
        "placement": "2nd Place",
        "misc": "for fun",
        "notes": "the penguin was too strong",
        "p1": 16626263,
        "p2": "",
        "p3": "",
        "p4": "",
        "p5": "",
        "p6": "",
        "p7": "",
        "p8": "",
        "p9": "",
        "p10": "",
        "p11": "",
        "p12": "",
        "p13": "",
        "p14": "",
        "p15": "",
        "p16": ""
    },
    "24": {
        "date": "April 16, 2022",
        "tourn_name": "Logical Osu!Cup Spring 2022",
        "team_name": "william",
        "forum": "https://osu.ppy.sh/community/forums/topics/1534137?n=1",
        "tourn_sheet": "https://docs.google.com/spreadsheets/d/1bXX7UyvHPzO2PZhgYjHXJbrK8SIx9Ve2lf94RKmBPYQ/edit#gid=683866025",
        "bracket": "https://challonge.com/LOC_2",
        "rank_range": "10k-50k",
        "seed": "29/32",
        "format": "2v2",
        "team_size": 4,
        "placement": "Round of 16",
        "misc": "",
        "notes": "fun little tournament with the homies also i am a terrible captain",
        "p1": 16626263,
        "p2": 20961291,
        "p3": 15885448,
        "p4": 19607568,
        "p5": "",
        "p6": "",
        "p7": "",
        "p8": "",
        "p9": "",
        "p10": "",
        "p11": "",
        "p12": "",
        "p13": "",
        "p14": "",
        "p15": "",
        "p16": ""
    },
    "25": {
        "date": "April 9, 2022",
        "tourn_name": "RANDOM MAP TOURNAMENT",
        "team_name": "good question",
        "forum": "https://osu.ppy.sh/community/forums/topics/1532938?n=1",
        "tourn_sheet": "https://docs.google.com/spreadsheets/d/1_VzFKPsipWh9XDjIBt6KCyZ4iXyMD9ciMaFfDzREsLk/edit#gid=1032691322",
        "bracket": "https://challonge.com/99v9pbla",
        "rank_range": "10k-40k",
        "seed": "10/64",
        "format": "2v2",
        "team_size": 3,
        "placement": "3rd Place",
        "misc": "shit maps",
        "notes": "loved my teammates they were very chill :D first tourney i got money from W",
        "p1": 16626263,
        "p2": 14174951,
        "p3": 10350809,
        "p4": "",
        "p5": "",
        "p6": "",
        "p7": "",
        "p8": "",
        "p9": "",
        "p10": "",
        "p11": "",
        "p12": "",
        "p13": "",
        "p14": "",
        "p15": "",
        "p16": ""
    },
    "26": {
        "date": "April 15, 2022",
        "tourn_name": "Duck Cup 3",
        "team_name": "Kusudama",
        "forum": "https://osu.ppy.sh/community/forums/topics/1532625?n=1",
        "tourn_sheet": "https://docs.google.com/spreadsheets/d/1Qr7kbhqFkt92UIA-2gnzSsQQZHNb8tNpeQY5x8MpDoI/edit#gid=2049468888",
        "bracket": "https://challonge.com/vf29toh0",
        "rank_range": "7.5k+",
        "seed": "13/32",
        "format": "2v2",
        "team_size": 3,
        "placement": "Quarterfinals",
        "misc": "",
        "notes": ":olluo: tb losses: 4",
        "p1": 9367683,
        "p2": 10382679,
        "p3": 16626263,
        "p4": "",
        "p5": "",
        "p6": "",
        "p7": "",
        "p8": "",
        "p9": "",
        "p10": "",
        "p11": "",
        "p12": "",
        "p13": "",
        "p14": "",
        "p15": "",
        "p16": ""
    },
    "27": {
        "date": "April 23, 2022",
        "tourn_name": "5 Digit World Cup Minor League",
        "team_name": "United States B",
        "forum": "https://osu.ppy.sh/community/forums/topics/1541806?n=1",
        "tourn_sheet": "https://docs.google.com/spreadsheets/d/15urVB4nAR1BnZ3J04TbpUpGthLhwso12BBGFbO2gH1I/edit",
        "bracket": "https://challonge.com/5wc_2022_ml",
        "rank_range": "10k-99k",
        "seed": "1/32",
        "format": "4v4",
        "team_size": 8,
        "placement": "1st Place",
        "misc": "",
        "notes": "第二轮 round 2 失败者 losers bracket 事件 incident air ball 空气球",
        "p1": 9526124,
        "p2": 16052525,
        "p3": 13445197,
        "p4": 11626378,
        "p5": 12324616,
        "p6": 3942633,
        "p7": 11612720,
        "p8": 16626263,
        "p9": "",
        "p10": "",
        "p11": "",
        "p12": "",
        "p13": "",
        "p14": "",
        "p15": "",
        "p16": ""
    },
    "28": {
        "date": "May 27, 2022",
        "tourn_name": "Konoha Cup 🍉 Splash Season",
        "team_name": "",
        "forum": "https://osu.ppy.sh/community/forums/topics/1545476?n=1",
        "tourn_sheet": "https://docs.google.com/spreadsheets/d/1Nv9Zv2sVRXG6c8K2cNHb9WL2whWksTqZqds_eZeiyyI/edit#gid=0",
        "bracket": "https://challonge.com/3x9qnd11",
        "rank_range": "20k-50k",
        "seed": "9/64",
        "format": "1v1",
        "team_size": 1,
        "placement": "Round of 16",
        "misc": "",
        "notes": "my worst tournament performance... probably cause i injured a nerve mid tournament and could not feel my aim hand. tb losses: 5",
        "p1": 16626263,
        "p2": "",
        "p3": "",
        "p4": "",
        "p5": "",
        "p6": "",
        "p7": "",
        "p8": "",
        "p9": "",
        "p10": "",
        "p11": "",
        "p12": "",
        "p13": "",
        "p14": "",
        "p15": "",
        "p16": ""
    },
    "29": {
        "date": "May 1, 2022",
        "tourn_name": "The Perennial",
        "team_name": "Daniel New Queen",
        "forum": "https://osu.ppy.sh/community/forums/topics/1565380?n=1",
        "tourn_sheet": "",
        "bracket": "",
        "rank_range": "Open Rank",
        "seed": "DNQ",
        "format": "4v4",
        "team_size": 8,
        "placement": "DNQ",
        "misc": "",
        "notes": "nice try",
        "p1": 9878349,
        "p2": 12045415,
        "p3": 12067984,
        "p4": 11847188,
        "p5": 4722369,
        "p6": 5427223,
        "p7": 3942633,
        "p8": 16626263,
        "p9": "",
        "p10": "",
        "p11": "",
        "p12": "",
        "p13": "",
        "p14": "",
        "p15": "",
        "p16": ""
    },
    "30": {
        "date": "June 9, 2022",
        "tourn_name": "Stage's Tranquility Tournament 3",
        "team_name": "Operation Killing Copper",
        "forum": "https://osu.ppy.sh/community/forums/topics/1567938",
        "tourn_sheet": "https://docs.google.com/spreadsheets/d/16o5Xg8RzujIc2y54G16ZI4mp3ZWTzAMR-69n0jW00Jw/edit",
        "bracket": "https://challonge.com/STT3",
        "rank_range": "10k-99k",
        "seed": "34/64",
        "format": "3v3",
        "team_size": 6,
        "placement": "Quarterfinals",
        "misc": "",
        "notes": "my arm was still dead yo. tb losses: 6",
        "p1": 7023000,
        "p2": 5427223,
        "p3": 12067984,
        "p4": 12045415,
        "p5": 3942633,
        "p6": 16626263,
        "p7": "",
        "p8": "",
        "p9": "",
        "p10": "",
        "p11": "",
        "p12": "",
        "p13": "",
        "p14": "",
        "p15": "",
        "p16": ""
    },
    "31": {
        "date": "June 13, 2022",
        "tourn_name": "5 Digit United States Cup 2022",
        "team_name": "California (South)",
        "forum": "https://osu.ppy.sh/community/forums/topics/1566956?n=1",
        "tourn_sheet": "https://docs.google.com/spreadsheets/d/1py5CCe7Z-IR8QmSwXm-RU1kueo82SSJRcIT-IdJfWgc/edit#gid=0",
        "bracket": "https://challonge.com/5USC2022",
        "rank_range": "7.5k-99k",
        "seed": "4/32",
        "format": "3v3",
        "team_size": 6,
        "placement": "3rd Place",
        "misc": "",
        "notes": "all hail diabolikhaa !!! ",
        "p1": 12720968,
        "p2": 12011021,
        "p3": 12727907,
        "p4": 7023000,
        "p5": 13445197,
        "p6": 16626263,
        "p7": "",
        "p8": "",
        "p9": "",
        "p10": "",
        "p11": "",
        "p12": "",
        "p13": "",
        "p14": "",
        "p15": "",
        "p16": ""
    },
    "32": {
        "date": "July 9, 2022",
        "tourn_name": "EST Summer Edition 2022",
        "team_name": "good question",
        "forum": "https://osu.ppy.sh/community/forums/topics/1586300?n=1",
        "tourn_sheet": "https://esttournaments.com/",
        "bracket": "https://challonge.com/estsummer2022",
        "rank_range": "25k-75k",
        "seed": "8/32",
        "format": "2v2",
        "team_size": 3,
        "placement": "3rd Place",
        "misc": "swiss",
        "notes": "deranked 5k ranks for this. to this day still waiting for the saikou merch to arrive",
        "p1": 16626263,
        "p2": 14174951,
        "p3": 10382679,
        "p4": "",
        "p5": "",
        "p6": "",
        "p7": "",
        "p8": "",
        "p9": "",
        "p10": "",
        "p11": "",
        "p12": "",
        "p13": "",
        "p14": "",
        "p15": "",
        "p16": ""
    },
    "33": {
        "date": "July 9, 2022",
        "tourn_name": "Hard Rock Cup 2",
        "team_name": ":esecolte:",
        "forum": "https://osu.ppy.sh/community/forums/topics/1596527?n=1",
        "tourn_sheet": "https://docs.google.com/spreadsheets/d/17MlekwUE6v2wbqcDB6F9fCubhS6B7gOKx1cS5YSit5Y/edit#gid=0",
        "bracket": "https://challonge.com/HardRockCup2",
        "rank_range": "Open Rank",
        "seed": "7/64",
        "format": "3v3",
        "team_size": 4,
        "placement": "Round of 16",
        "misc": "3 tiers",
        "notes": "idk what happened lol i dont play hard rock",
        "p1": 7701428,
        "p2": 2546001,
        "p3": 9367683,
        "p4": 16626263,
        "p5": "",
        "p6": "",
        "p7": "",
        "p8": "",
        "p9": "",
        "p10": "",
        "p11": "",
        "p12": "",
        "p13": "",
        "p14": "",
        "p15": "",
        "p16": ""
    },
    "34": {
        "date": "August 8, 2022",
        "tourn_name": "Visual Novel Duo Brackets",
        "team_name": "good question",
        "forum": "https://osu.ppy.sh/community/forums/topics/1609110?n=1",
        "tourn_sheet": "https://docs.google.com/spreadsheets/d/1OGfhu3S3W8XhLn2rgCL76zt5ivbG6OoECOYqqTKRvyA/edit#gid=1227639000",
        "bracket": "https://challonge.com/vndb",
        "rank_range": "10k-99k",
        "seed": "4/64",
        "format": "2v2",
        "team_size": 2,
        "placement": "3rd Place",
        "misc": "all eroge maps",
        "notes": "me when the rank 30k player gets 450k avg on the 7 star grands pool",
        "p1": 12324616,
        "p2": 16626263,
        "p3": "",
        "p4": "",
        "p5": "",
        "p6": "",
        "p7": "",
        "p8": "",
        "p9": "",
        "p10": "",
        "p11": "",
        "p12": "",
        "p13": "",
        "p14": "",
        "p15": "",
        "p16": ""
    },
    "35": {
        "date": "August 1, 2022",
        "tourn_name": "Konoha Dessert Menu",
        "team_name": "kakuzetsu thanos",
        "forum": "",
        "tourn_sheet": "https://docs.google.com/spreadsheets/d/1p-AUTGsE3LC_PhM2pFn2x2jJBouUtnuGM4EImZs8xe8/edit#gid=1392300164",
        "bracket": "https://challonge.com/wjqf6zuj",
        "rank_range": "7k-27k",
        "seed": "5/16",
        "format": "2v2",
        "team_size": 4,
        "placement": "3rd Place",
        "misc": "",
        "notes": "the maps got a bit too hard. carlosflow le gana",
        "p1": 5427223,
        "p2": 9878349,
        "p3": 7023000,
        "p4": 16626263,
        "p5": "",
        "p6": "",
        "p7": "",
        "p8": "",
        "p9": "",
        "p10": "",
        "p11": "",
        "p12": "",
        "p13": "",
        "p14": "",
        "p15": "",
        "p16": ""
    },
    "36": {
        "date": "August 19, 2022",
        "tourn_name": "CES Gaming osu! Intermediate 2022",
        "team_name": "",
        "forum": "https://osu.ppy.sh/community/forums/topics/1623183?n=1",
        "tourn_sheet": "https://docs.google.com/spreadsheets/d/11uBRkS-fmr-Xi3gar6T4lBMdVNth14C6Nu4oxI2yMYc/edit#gid=2048134981",
        "bracket": "https://challonge.com/osuintermediate2022",
        "rank_range": "10k-99k",
        "seed": "36/64",
        "format": "1v1",
        "team_size": 1,
        "placement": "Round of 64",
        "misc": "",
        "notes": "what?? a 5 digit 1v1 tournament since the first time in forever?? that sounds awesome lemme sig- oh pools are 5.4 stars",
        "p1": 16626263,
        "p2": "",
        "p3": "",
        "p4": "",
        "p5": "",
        "p6": "",
        "p7": "",
        "p8": "",
        "p9": "",
        "p10": "",
        "p11": "",
        "p12": "",
        "p13": "",
        "p14": "",
        "p15": "",
        "p16": ""
    },
    "37": {
        "date": "September 3, 2022",
        "tourn_name": "5 Digit Draft Cup: 2022",
        "team_name": "fruit",
        "forum": "https://osu.ppy.sh/community/forums/topics/1627822",
        "tourn_sheet": "https://docs.google.com/spreadsheets/d/1jQQXqJ4cjj04GclfRStPiWSJCqYpBb7oHMRLq2VMLLA/edit#gid=0",
        "bracket": "https://challonge.com/5DDC2022",
        "rank_range": "10k-99k",
        "seed": "6/16",
        "format": "4v4",
        "team_size": 8,
        "placement": "Semifinals",
        "misc": "draft ",
        "notes": "drafted a for fun team. had fun. met some chill people with great potential.",
        "p1": 16626263,
        "p2": 4010492,
        "p3": 14396453,
        "p4": 10562797,
        "p5": 10716391,
        "p6": 17996877,
        "p7": 25102317,
        "p8": 12720968,
        "p9": "",
        "p10": "",
        "p11": "",
        "p12": "",
        "p13": "",
        "p14": "",
        "p15": "",
        "p16": ""
    },
    "38": {
        "date": "September 19, 2022",
        "tourn_name": "Hitomi's Hidden Extra",
        "team_name": "",
        "forum": "https://osu.ppy.sh/community/forums/topics/1629951?n=1",
        "tourn_sheet": "https://docs.google.com/spreadsheets/d/1sQ8JCsX_DnpuwmIXOQMdZfEwtM9tXq0e_tVQ2SW_B6I/edit#gid=0",
        "bracket": "https://challonge.com/hhe_osu",
        "rank_range": "Open Rank",
        "seed": "23/32",
        "format": "1v1",
        "team_size": 1,
        "placement": "Round of 16",
        "misc": "all hidden",
        "notes": "first time qualifying for open rank 1v1. also had the worst tiebreaker loss by 900 score",
        "p1": 16626263,
        "p2": "",
        "p3": "",
        "p4": "",
        "p5": "",
        "p6": "",
        "p7": "",
        "p8": "",
        "p9": "",
        "p10": "",
        "p11": "",
        "p12": "",
        "p13": "",
        "p14": "",
        "p15": "",
        "p16": ""
    },
    "39": {
        "date": "September 9, 2022",
        "tourn_name": "Toti's International Tournament Season 1 ",
        "team_name": "the penguin from spy x family",
        "forum": "https://osu.ppy.sh/community/forums/topics/1623197?n=1",
        "tourn_sheet": "https://docs.google.com/spreadsheets/d/1-qIzP10XCl2-feRsrrTciP-vLE8GlKVwKj_kgx1IgnU/edit#gid=0",
        "bracket": "https://challonge.com/Toti1",
        "rank_range": "10k-99k",
        "seed": "14/32",
        "format": "2v2",
        "team_size": 4,
        "placement": "Semifinals",
        "misc": "no bws",
        "notes": "tb losses: 8",
        "p1": 11526714,
        "p2": 7023000,
        "p3": 12045415,
        "p4": 16626263,
        "p5": "",
        "p6": "",
        "p7": "",
        "p8": "",
        "p9": "",
        "p10": "",
        "p11": "",
        "p12": "",
        "p13": "",
        "p14": "",
        "p15": "",
        "p16": ""
    },
    "40": {
        "date": "September 17, 2022",
        "tourn_name": "Nocy's Second Voli-tile Clash",
        "team_name": "ocaip hijueputa 2",
        "forum": "https://osu.ppy.sh/community/forums/topics/1627934?n=1",
        "tourn_sheet": "https://docs.google.com/spreadsheets/d/1QiD_FXpXPEIV652pmG8kJQyeSmmsaLK--Wv20hnoYYo/edit#gid=628128412",
        "bracket": "https://challonge.com/N2VC",
        "rank_range": "10k+",
        "seed": "14/32",
        "format": "3v3",
        "team_size": 5,
        "placement": "Semifinals",
        "misc": "deviant cards ",
        "notes": "ended pretty badly. who knew that you wouldnt play well when youve been playing osu for eight hours. tb losses: 10 (we lost two)",
        "p1": 8921554,
        "p2": 10382679,
        "p3": 9367683,
        "p4": 8779023,
        "p5": 16626263,
        "p6": "",
        "p7": "",
        "p8": "",
        "p9": "",
        "p10": "",
        "p11": "",
        "p12": "",
        "p13": "",
        "p14": "",
        "p15": "",
        "p16": ""
    },
    "41": {
        "date": "September 30, 2022",
        "tourn_name": "Duck Cup: Mallard Edition",
        "team_name": "bomb seal",
        "forum": "https://osu.ppy.sh/community/forums/topics/1629932?n=1",
        "tourn_sheet": "https://docs.google.com/spreadsheets/d/1Nozp0XGD_MqHnQFM3p0xud_vIyTYppxI-V1gMVDkNGQ/edit#gid=0",
        "bracket": "https://challonge.com/mallardcup4",
        "rank_range": "7.5k+",
        "seed": "10/32",
        "format": "2v2",
        "team_size": 3,
        "placement": "Quarterfinals",
        "misc": "",
        "notes": "mb",
        "p1": 5427223,
        "p2": 4529885,
        "p3": 16626263,
        "p4": "",
        "p5": "",
        "p6": "",
        "p7": "",
        "p8": "",
        "p9": "",
        "p10": "",
        "p11": "",
        "p12": "",
        "p13": "",
        "p14": "",
        "p15": "",
        "p16": ""
    },
    "42": {
        "date": "October 1, 2022",
        "tourn_name": "osu! Collegiate League Standard",
        "team_name": "University of California - Irvine A",
        "forum": "https://osu.ppy.sh/community/forums/topics/1641859?n=1",
        "tourn_sheet": "https://docs.google.com/spreadsheets/d/1mty-nrX_u4ucWfzPm69RXcUDX-5dYbgwBlbjkXCGnA8/edit#gid=0",
        "bracket": "https://challonge.com/communities/osuCL",
        "rank_range": "Open Rank",
        "seed": "DNQ",
        "format": "2v2",
        "team_size": 4,
        "placement": "DNQ",
        "misc": "",
        "notes": "i farmed 1k pp in one night to get our school to the open rank range that was pretty funny",
        "p1": 12437342,
        "p2": 10350809,
        "p3": 14520271,
        "p4": 16626263,
        "p5": "",
        "p6": "",
        "p7": "",
        "p8": "",
        "p9": "",
        "p10": "",
        "p11": "",
        "p12": "",
        "p13": "",
        "p14": "",
        "p15": "",
        "p16": ""
    },
    "43": {
        "date": "October 5, 2022",
        "tourn_name": "copper world cup 2",
        "team_name": "pill enjoyers",
        "forum": "",
        "tourn_sheet": "https://docs.google.com/spreadsheets/d/1XkleRl3HVptvYKOOI3OTvaO_9a56hxrGXbBjB8TUx5M/edit#gid=0",
        "bracket": "https://challonge.com/cwc2babylesgo",
        "rank_range": "Open Rank",
        "seed": "?",
        "format": "3v3",
        "team_size": 4,
        "placement": "Semifinals",
        "misc": "draft",
        "notes": "ethan",
        "p1": 16626263,
        "p2": 10634348,
        "p3": 15928955,
        "p4": 13605288,
        "p5": "",
        "p6": "",
        "p7": "",
        "p8": "",
        "p9": "",
        "p10": "",
        "p11": "",
        "p12": "",
        "p13": "",
        "p14": "",
        "p15": "",
        "p16": ""
    },
    "44": {
        "date": "November 4, 2022",
        "tourn_name": "Resurrection Cup: Cataclysm Contest",
        "team_name": "",
        "forum": "https://osu.ppy.sh/community/forums/topics/1657085?n=1",
        "tourn_sheet": "https://docs.google.com/spreadsheets/d/16Qff9ZYPU5hyYiRgL981Q8rHv39YH0_h6NZrok_BVog/edit#gid=278729146",
        "bracket": "https://challonge.com/RESCCC",
        "rank_range": "Open Rank",
        "seed": "14/32",
        "format": "1v1",
        "team_size": 1,
        "placement": "Quarterfinals",
        "misc": "super high sr",
        "notes": "finally got to play 9 star aim maps in tourney :heart_eyes:",
        "p1": 16626263,
        "p2": "",
        "p3": "",
        "p4": "",
        "p5": "",
        "p6": "",
        "p7": "",
        "p8": "",
        "p9": "",
        "p10": "",
        "p11": "",
        "p12": "",
        "p13": "",
        "p14": "",
        "p15": "",
        "p16": ""
    },
    "45": {
        "date": "November 19, 2022",
        "tourn_name": "BubblyQT osu! Party 4 ",
        "team_name": "good question",
        "forum": "https://osu.ppy.sh/community/forums/topics/1664573?n=1",
        "tourn_sheet": "https://docs.google.com/spreadsheets/d/1rP_WlLqiroLJsneaIkZ9zvfyL6vXgLtpkMF3t8Yx9ac/edit#gid=0",
        "bracket": "",
        "rank_range": "Open Rank",
        "seed": "40/64",
        "format": "2v2",
        "team_size": 4,
        "placement": "Round of 16",
        "misc": "",
        "notes": "washington osu",
        "p1": 16626263,
        "p2": 7438459,
        "p3": 11847188,
        "p4": 6094894,
        "p5": "",
        "p6": "",
        "p7": "",
        "p8": "",
        "p9": "",
        "p10": "",
        "p11": "",
        "p12": "",
        "p13": "",
        "p14": "",
        "p15": "",
        "p16": ""
    },
    "46": {
        "date": "November 28, 2022",
        "tourn_name": "osu!England vs The World",
        "team_name": "",
        "forum": "https://osu.ppy.sh/community/forums/topics/1666296?n=1",
        "tourn_sheet": "https://docs.google.com/spreadsheets/d/1FVCZqZBsIsFJg-vP0aEKHIEbdSoO2m2Q1aaBXtCNi1k/edit#gid=1749102088",
        "bracket": "",
        "rank_range": "Open Rank",
        "seed": "3/16",
        "format": "2v2",
        "team_size": 4,
        "placement": "Finals",
        "misc": "single elim",
        "notes": "go saudi arabia",
        "p1": 22461441,
        "p2": 10170668,
        "p3": 9878349,
        "p4": 16626263,
        "p5": "",
        "p6": "",
        "p7": "",
        "p8": "",
        "p9": "",
        "p10": "",
        "p11": "",
        "p12": "",
        "p13": "",
        "p14": "",
        "p15": "",
        "p16": ""
    },
    "47": {
        "date": "November 12, 2022",
        "tourn_name": "Piper's UR Cup",
        "team_name": "",
        "forum": "https://osu.ppy.sh/community/forums/topics/1671028?n=1",
        "tourn_sheet": "https://docs.google.com/spreadsheets/d/1LR7rAHGz-vJ-09i4OGiww1Qzi3FMkkAuOWKp_-67P2U/edit?resourcekey=undefined#gid=270266282",
        "bracket": "",
        "rank_range": "Open Rank",
        "seed": "DNQ",
        "format": "1v1",
        "team_size": 1,
        "placement": "DNQ",
        "misc": "UR win con",
        "notes": "failed a map so one of my scores didnt count",
        "p1": 16626263,
        "p2": "",
        "p3": "",
        "p4": "",
        "p5": "",
        "p6": "",
        "p7": "",
        "p8": "",
        "p9": "",
        "p10": "",
        "p11": "",
        "p12": "",
        "p13": "",
        "p14": "",
        "p15": "",
        "p16": ""
    },
    "48": {
        "date": "November 12, 2022",
        "tourn_name": "Aim Knockout Battle Royale",
        "team_name": "",
        "forum": "",
        "tourn_sheet": "https://docs.google.com/spreadsheets/d/1uBirjJwTF9g4JR5uZqO5kViflORn4qLgWXQrzC-Swdw/edit#gid=323118340",
        "bracket": "",
        "rank_range": "Open Rank",
        "seed": "9/16",
        "format": "1v1",
        "team_size": 1,
        "placement": "2nd Place",
        "misc": "closed tourney",
        "notes": "person with highest misscount gets eliminated after every map.  i got dunked on by whitecat's son in finals",
        "p1": 16626263,
        "p2": "",
        "p3": "",
        "p4": "",
        "p5": "",
        "p6": "",
        "p7": "",
        "p8": "",
        "p9": "",
        "p10": "",
        "p11": "",
        "p12": "",
        "p13": "",
        "p14": "",
        "p15": "",
        "p16": ""
    },
    "49": {
        "date": "November 19, 2022",
        "tourn_name": "pilk all rounder tournament",
        "team_name": "",
        "forum": "",
        "tourn_sheet": "https://docs.google.com/spreadsheets/d/1FoH10Gz0zjtavhRrZniI1geH-ICphSqmyokPkF6UcEs/edit#gid=1392965369",
        "bracket": "https://challonge.com/PARTtournament",
        "rank_range": "Open Rank",
        "seed": "2/16",
        "format": "1v1",
        "team_size": 1,
        "placement": "2nd Place",
        "misc": "",
        "notes": "https://media.discordapp.net/attachments/975823343368417383/1074132526949478470/ristel.png",
        "p1": 16626263,
        "p2": "",
        "p3": "",
        "p4": "",
        "p5": "",
        "p6": "",
        "p7": "",
        "p8": "",
        "p9": "",
        "p10": "",
        "p11": "",
        "p12": "",
        "p13": "",
        "p14": "",
        "p15": "",
        "p16": ""
    },
    "50": {
        "date": "January 2, 2023",
        "tourn_name": "Frost Blossom Cup",
        "team_name": "good question",
        "forum": "https://osu.ppy.sh/community/forums/topics/1685751?n=1",
        "tourn_sheet": "https://docs.google.com/spreadsheets/d/1OH2eOsChDZ2tIyKPW4eGbZ6vIqz-RDCL-zxuNfckIL4/edit#gid=284105102",
        "bracket": "https://challonge.com/de/FrostBlossomCup2023",
        "rank_range": "Open Rank",
        "seed": "37/64",
        "format": "2v2",
        "team_size": 4,
        "placement": "Round of 16",
        "misc": "",
        "notes": "so close to getting out of ro16 :sob:",
        "p1": 16626263,
        "p2": 9507565,
        "p3": 5283014,
        "p4": 9526124,
        "p5": "",
        "p6": "",
        "p7": "",
        "p8": "",
        "p9": "",
        "p10": "",
        "p11": "",
        "p12": "",
        "p13": "",
        "p14": "",
        "p15": "",
        "p16": ""
    },
    "51": {
        "date": "February 4, 2023",
        "tourn_name": "Pandemonium Intercontinental Showdown 2023",
        "team_name": "",
        "forum": "https://osu.ppy.sh/community/forums/topics/1693798?n=1",
        "tourn_sheet": "https://docs.google.com/spreadsheets/d/1F4yLlwbp9-NwlLMFyxWwBZdL9hvPYiGamzc3ftEH118/edit#gid=40418357",
        "bracket": "",
        "rank_range": "Open Rank",
        "seed": "DNQ",
        "format": "1v1",
        "team_size": 1,
        "placement": "DNQ",
        "misc": "",
        "notes": "bruh",
        "p1": 16626263,
        "p2": "",
        "p3": "",
        "p4": "",
        "p5": "",
        "p6": "",
        "p7": "",
        "p8": "",
        "p9": "",
        "p10": "",
        "p11": "",
        "p12": "",
        "p13": "",
        "p14": "",
        "p15": "",
        "p16": ""
    },
    "52": {
        "date": "January 29, 2023",
        "tourn_name": "osu! Collegiate League Winter 2023",
        "team_name": "University of California - Irvine A",
        "forum": "https://osu.ppy.sh/community/forums/topics/1699577?n=1",
        "tourn_sheet": "https://docs.google.com/spreadsheets/d/112ABFIwDrn6j54k-gU5Ui8Xc3V6VDHUFPO5Wbn5zsf4/edit#gid=0",
        "bracket": "https://challonge.com/communities/osuCL",
        "rank_range": "Open Rank",
        "seed": "26/32",
        "format": "2v2",
        "team_size": 4,
        "placement": "Round of 16",
        "misc": "",
        "notes": "Oops!",
        "p1": 10350809,
        "p2": 10938118,
        "p3": 10805397,
        "p4": 16626263,
        "p5": "",
        "p6": "",
        "p7": "",
        "p8": "",
        "p9": "",
        "p10": "",
        "p11": "",
        "p12": "",
        "p13": "",
        "p14": "",
        "p15": "",
        "p16": ""
    },
    "53": {
        "date": "February 18, 2023",
        "tourn_name": "Fifth osu! Winter LAN",
        "team_name": "",
        "forum": "https://osu.ppy.sh/community/forums/topics/1715374?n=1",
        "tourn_sheet": "https://docs.google.com/spreadsheets/u/1/d/1TDehC4mscWbR8epCRpze81VZi3Z9hRGFBOR6tHgsq5Q/edit?usp=sharing",
        "bracket": "https://challonge.com/FOWL_Standard",
        "rank_range": "Open Rank",
        "seed": "7/16",
        "format": "1v1",
        "team_size": 1,
        "placement": "Semifinals",
        "misc": "lan",
        "notes": "13 hour osu session:",
        "p1": 16626263,
        "p2": "",
        "p3": "",
        "p4": "",
        "p5": "",
        "p6": "",
        "p7": "",
        "p8": "",
        "p9": "",
        "p10": "",
        "p11": "",
        "p12": "",
        "p13": "",
        "p14": "",
        "p15": "",
        "p16": ""
    },
    "54": {
        "date": "February 25, 2023",
        "tourn_name": "Star-Spangled Tournament",
        "team_name": "",
        "forum": "https://osu.ppy.sh/community/forums/topics/1715837?n=1",
        "tourn_sheet": "https://docs.google.com/spreadsheets/d/1VR9iLDWwm-Y0XuUbBAm2Y4FFvS94hRagOlMwE7NAGZ4/edit#gid=0",
        "bracket": "",
        "rank_range": "950+",
        "seed": "",
        "format": "1v1",
        "team_size": 1,
        "placement": "Finals",
        "misc": "",
        "notes": "def should not have placed this high Lol",
        "p1": 16626263,
        "p2": "",
        "p3": "",
        "p4": "",
        "p5": "",
        "p6": "",
        "p7": "",
        "p8": "",
        "p9": "",
        "p10": "",
        "p11": "",
        "p12": "",
        "p13": "",
        "p14": "",
        "p15": "",
        "p16": ""
    },
    "55": {
        "date": "February 11, 2023",
        "tourn_name": "osu! Goodbye Despair",
        "team_name": "peepoHappy",
        "forum": "https://osu.ppy.sh/community/forums/topics/1705962?n=1",
        "tourn_sheet": "https://docs.google.com/spreadsheets/d/1x2H2JqSrYwRNmm0Z66zBHPn7P-gDF_ysoKkJ-Q5DC-w/edit#gid=1097183912",
        "bracket": "https://challonge.com/ogbd",
        "rank_range": "1k-30k",
        "seed": "N/A",
        "format": "4v4",
        "team_size": 8,
        "placement": "Quarterfinals",
        "misc": "Suiji style",
        "notes": "why is nm3 teh most intable thingi nthe world arghoaeugha",
        "p1": 5281485,
        "p2": 11718072,
        "p3": 9924405,
        "p4": 13452017,
        "p5": 16626263,
        "p6": 17348593,
        "p7": 13205755,
        "p8": 6595616,
        "p9": "",
        "p10": "",
        "p11": "",
        "p12": "",
        "p13": "",
        "p14": "",
        "p15": "",
        "p16": ""
    },
    "56": {
        "date": "February 26, 2023",
        "tourn_name": "Ivy Cup 2",
        "team_name": "Wenches and Mead",
        "forum": "",
        "tourn_sheet": "https://docs.google.com/spreadsheets/d/1O9m2HlIBqGYkQK4cHmpgPRRTacjxWLk6lIwgfKUQkzU/edit#gid=0",
        "bracket": "https://challonge.com/ivycup2tier1",
        "rank_range": "Open Rank",
        "seed": "1/4",
        "format": "2v2",
        "team_size": 4,
        "placement": "Ongoing",
        "misc": "one ivy league member in for each map",
        "notes": "",
        "p1": 3162076,
        "p2": 4681677,
        "p3": 5427223,
        "p4": 16626263,
        "p5": "",
        "p6": "",
        "p7": "",
        "p8": "",
        "p9": "",
        "p10": "",
        "p11": "",
        "p12": "",
        "p13": "",
        "p14": "",
        "p15": "",
        "p16": ""
    },
    "57": {
        "date": "March 17, 2023",
        "tourn_name": "United Cup",
        "team_name": "plink",
        "forum": "https://osu.ppy.sh/community/forums/topics/1712026?n=1",
        "tourn_sheet": "https://docs.google.com/spreadsheets/d/12gJc9Y2ysqF2seaDNTk1W5ISX2WJZNIB_m6819q-4MM/edit#gid=0",
        "bracket": "https://challonge.com/3jvbemcu",
        "rank_range": "1k-25k+25k-50k",
        "seed": "6/32",
        "format": "4v4",
        "team_size": 8,
        "placement": "Ongoing",
        "misc": "every pool has united",
        "notes": "",
        "p1": 12904237,
        "p2": 11536421,
        "p3": 11612720,
        "p4": 23124445,
        "p5": 7989469,
        "p6": 10201439,
        "p7": 16679145,
        "p8": 16626263,
        "p9": "",
        "p10": "",
        "p11": "",
        "p12": "",
        "p13": "",
        "p14": "",
        "p15": "",
        "p16": ""
    },
    "58": {
        "date": "March 22, 2023",
        "tourn_name": "Floral Fury Faceoff",
        "team_name": "WASHINGTON SUPER KITTIES",
        "forum": "https://osu.ppy.sh/community/forums/topics/1724540?n=1",
        "tourn_sheet": "https://docs.google.com/spreadsheets/d/13qgzHMgDww21wh-CFPYv2VdKKuM-G6mKdol9hRN1UY4/edit#gid=1594626835",
        "bracket": "https://challonge.com/FloralFuryFaceoff",
        "rank_range": "300-50000",
        "seed": "20/32",
        "format": "4v4",
        "team_size": 8,
        "placement": "Ongoing",
        "misc": "",
        "notes": "",
        "p1": 8204345,
        "p2": 10634348,
        "p3": 12133744,
        "p4": 7246954,
        "p5": 7673411,
        "p6": 19154954,
        "p7": 3189069,
        "p8": 16626263,
        "p9": "",
        "p10": "",
        "p11": "",
        "p12": "",
        "p13": "",
        "p14": "",
        "p15": "",
        "p16": ""
    },
    "59": {
        "date": "April 7, 2023",
        "tourn_name": "Jas' Winter Duo Cup",
        "team_name": "good question",
        "forum": "https://osu.ppy.sh/community/forums/topics/1725183?n=1",
        "tourn_sheet": "https://docs.google.com/spreadsheets/d/1fHo6ybMA_uoNRIm0LAFtF_seUbaVeLTCfbpRt1iGLqY/edit?usp=sharing",
        "bracket": "https://challonge.com/JWC23",
        "rank_range": "1k-20k",
        "seed": "",
        "format": "2v2",
        "team_size": 2,
        "placement": "Upcoming",
        "misc": "",
        "notes": "",
        "p1": 16626263,
        "p2": 8208289,
        "p3": "",
        "p4": "",
        "p5": "",
        "p6": "",
        "p7": "",
        "p8": "",
        "p9": "",
        "p10": "",
        "p11": "",
        "p12": "",
        "p13": "",
        "p14": "",
        "p15": "",
        "p16": ""
    },
    "60": {
        "date": "April 14, 2023",
        "tourn_name": "Gary's Spring Hidden Tournament 3",
        "team_name": "good question",
        "forum": "https://osu.ppy.sh/community/forums/topics/1733328?n=1",
        "tourn_sheet": "https://docs.google.com/spreadsheets/d/1rRo9bIOIceHprL97BgzEAXxxNu7uysBCx14WPCdNH00/edit#gid=1908109648",
        "bracket": "",
        "rank_range": "2k+",
        "seed": "",
        "format": "2v2",
        "team_size": 4,
        "placement": "Upcoming",
        "misc": "",
        "notes": "",
        "p1": 16626263,
        "p2": 10634348,
        "p3": 3149395,
        "p4": 11106929,
        "p5": "",
        "p6": "",
        "p7": "",
        "p8": "",
        "p9": "",
        "p10": "",
        "p11": "",
        "p12": "",
        "p13": "",
        "p14": "",
        "p15": "",
        "p16": ""
    }
}